{"libsodium-tests":{"repeat":"1","result":{"aead_aegis128l.wasm":{"avg":11186805000,"var":0},"aead_aegis256.wasm":{"avg":18427875000,"var":0},"aead_chacha20poly1305.wasm":{"avg":216615000,"var":0},"aead_chacha20poly13052.wasm":{"avg":313100000,"var":0},"aead_xchacha20poly1305.wasm":{"avg":203795000,"var":0},"auth.wasm":{"avg":61885000,"var":0},"auth2.wasm":{"avg":3520000,"var":0},"auth3.wasm":{"avg":6090000,"var":0},"auth5.wasm":{"avg":30038515000,"var":0},"auth6.wasm":{"avg":4995000,"var":0},"auth7.wasm":{"avg":16690980000,"var":0},"box.wasm":{"avg":369010000,"var":0},"box2.wasm":{"avg":375760000,"var":0},"box7.wasm":{"avg":374108595000,"var":0},"box8.wasm":{"avg":1106337500000,"var":0},"box_easy.wasm":{"avg":757145000,"var":0},"box_easy2.wasm":{"avg":50769635000,"var":0},"box_seal.wasm":{"avg":2029765000,"var":0},"box_seed.wasm":{"avg":67565000,"var":0},"chacha20.wasm":{"avg":766400000,"var":0},"codecs.wasm":{"avg":1427290000,"var":0},"core3.wasm":{"avg":70593860000,"var":0},"core_ed25519.wasm":{"avg":1330837420000,"var":0},"core_ed25519_h2c.wasm":{"avg":2026825000,"var":0},"core_ristretto255.wasm":{"avg":1492295955000,"var":0},"ed25519_convert.wasm":{"avg":158866115000,"var":0},"generichash.wasm":{"avg":577655000,"var":0},"generichash2.wasm":{"avg":64265000,"var":0},"generichash3.wasm":{"avg":65975000,"var":0},"hash.wasm":{"avg":6615000,"var":0},"hash3.wasm":{"avg":1615000,"var":0},"kdf.wasm":{"avg":48735000,"var":0},"kdf_hkdf.wasm":{"avg":1530405000,"var":0},"keygen.wasm":{"avg":14635000,"var":0},"kx.wasm":{"avg":2216355000,"var":0},"metamorphic.wasm":{"avg":32391690000,"var":0},"onetimeauth.wasm":{"avg":910000,"var":0},"onetimeauth2.wasm":{"avg":0,"var":0},"onetimeauth7.wasm":{"avg":6079590000,"var":0},"pwhash_argon2i.wasm":{"avg":360573900000,"var":0},"pwhash_argon2id.wasm":{"avg":435111300000,"var":0},"pwhash_scrypt.wasm":{"avg":1198538110000,"var":0},"pwhash_scrypt_ll.wasm":{"avg":80282320000,"var":0},"randombytes.wasm":{"avg":5665955000,"var":0},"scalarmult.wasm":{"avg":666450000,"var":0},"scalarmult2.wasm":{"avg":73265000,"var":0},"scalarmult5.wasm":{"avg":182065000,"var":0},"scalarmult6.wasm":{"avg":180740000,"var":0},"scalarmult7.wasm":{"avg":362295000,"var":0},"scalarmult8.wasm":{"avg":10717650000,"var":0},"scalarmult_ed25519.wasm":{"avg":3709675000,"var":0},"scalarmult_ristretto255.wasm":{"avg":4402965000,"var":0},"secretbox.wasm":{"avg":2825000,"var":0},"secretbox2.wasm":{"avg":1690000,"var":0},"secretbox7.wasm":{"avg":8620105000,"var":0},"secretbox8.wasm":{"avg":19709095000,"var":0},"secretbox_easy.wasm":{"avg":14355000,"var":0},"secretbox_easy2.wasm":{"avg":32515350000,"var":0},"secretstream_xchacha20poly1305.wasm":{"avg":104715000,"var":0},"shorthash.wasm":{"avg":1785000,"var":0},"sign.wasm":{"avg":662513060000,"var":0},"sign2.wasm":{"avg":1012040000,"var":0},"siphashx24.wasm":{"avg":2265000,"var":0},"sodium_utils.wasm":{"avg":24502195000,"var":0},"stream.wasm":{"avg":51464820000,"var":0},"stream2.wasm":{"avg":42680110000,"var":0},"stream3.wasm":{"avg":410000,"var":0},"stream4.wasm":{"avg":770000,"var":0},"verify1.wasm":{"avg":77800190000,"var":0},"xchacha20.wasm":{"avg":11795825000,"var":0}}}}
