{"libsodium-tests":{"repeat":"1","result":{"aead_aegis128l.wasm":{"avg":11223090000,"var":0},"aead_aegis256.wasm":{"avg":12450915000,"var":0},"aead_chacha20poly1305.wasm":{"avg":211250000,"var":0},"aead_chacha20poly13052.wasm":{"avg":309015000,"var":0},"aead_xchacha20poly1305.wasm":{"avg":202060000,"var":0},"auth.wasm":{"avg":61950000,"var":0},"auth2.wasm":{"avg":2885000,"var":0},"auth3.wasm":{"avg":5885000,"var":0},"auth5.wasm":{"avg":30002480000,"var":0},"auth6.wasm":{"avg":5430000,"var":0},"auth7.wasm":{"avg":16855055000,"var":0},"box.wasm":{"avg":371480000,"var":0},"box2.wasm":{"avg":377595000,"var":0},"box7.wasm":{"avg":365735770000,"var":0},"box8.wasm":{"avg":1098490925000,"var":0},"box_easy.wasm":{"avg":748530000,"var":0},"box_easy2.wasm":{"avg":50496485000,"var":0},"box_seal.wasm":{"avg":2034105000,"var":0},"box_seed.wasm":{"avg":64330000,"var":0},"chacha20.wasm":{"avg":766635000,"var":0},"codecs.wasm":{"avg":1426960000,"var":0},"core3.wasm":{"avg":70884685000,"var":0},"core_ed25519.wasm":{"avg":1331847490000,"var":0},"core_ed25519_h2c.wasm":{"avg":2030900000,"var":0},"core_ristretto255.wasm":{"avg":1490083340000,"var":0},"ed25519_convert.wasm":{"avg":158606180000,"var":0},"generichash.wasm":{"avg":576200000,"var":0},"generichash2.wasm":{"avg":64770000,"var":0},"generichash3.wasm":{"avg":66715000,"var":0},"hash.wasm":{"avg":6830000,"var":0},"hash3.wasm":{"avg":1410000,"var":0},"kdf.wasm":{"avg":47655000,"var":0},"kdf_hkdf.wasm":{"avg":1532995000,"var":0},"keygen.wasm":{"avg":14160000,"var":0},"kx.wasm":{"avg":2198420000,"var":0},"metamorphic.wasm":{"avg":35216720000,"var":0},"onetimeauth.wasm":{"avg":920000,"var":0},"onetimeauth2.wasm":{"avg":0,"var":0},"onetimeauth7.wasm":{"avg":6081150000,"var":0},"pwhash_argon2i.wasm":{"avg":363579690000,"var":0},"pwhash_argon2id.wasm":{"avg":414767470000,"var":0},"pwhash_scrypt.wasm":{"avg":1244433895000,"var":0},"pwhash_scrypt_ll.wasm":{"avg":81482185000,"var":0},"randombytes.wasm":{"avg":5652500000,"var":0},"scalarmult.wasm":{"avg":665205000,"var":0},"scalarmult2.wasm":{"avg":63010000,"var":0},"scalarmult5.wasm":{"avg":180945000,"var":0},"scalarmult6.wasm":{"avg":184255000,"var":0},"scalarmult7.wasm":{"avg":363600000,"var":0},"scalarmult8.wasm":{"avg":10742280000,"var":0},"scalarmult_ed25519.wasm":{"avg":3709115000,"var":0},"scalarmult_ristretto255.wasm":{"avg":4385035000,"var":0},"secretbox.wasm":{"avg":3015000,"var":0},"secretbox2.wasm":{"avg":1615000,"var":0},"secretbox7.wasm":{"avg":8644425000,"var":0},"secretbox8.wasm":{"avg":19891740000,"var":0},"secretbox_easy.wasm":{"avg":14290000,"var":0},"secretbox_easy2.wasm":{"avg":30181305000,"var":0},"secretstream_xchacha20poly1305.wasm":{"avg":104605000,"var":0},"shorthash.wasm":{"avg":1770000,"var":0},"sign.wasm":{"avg":662410870000,"var":0},"sign2.wasm":{"avg":1022295000,"var":0},"siphashx24.wasm":{"avg":1820000,"var":0},"sodium_utils.wasm":{"avg":24615995000,"var":0},"stream.wasm":{"avg":51457880000,"var":0},"stream2.wasm":{"avg":42762675000,"var":0},"stream3.wasm":{"avg":440000,"var":0},"stream4.wasm":{"avg":780000,"var":0},"verify1.wasm":{"avg":76978090000,"var":0},"xchacha20.wasm":{"avg":11768180000,"var":0}}}}
