{"libsodium-tests":{"repeat":"1","result":{"aead_aegis128l.wasm":{"avg":7265040000,"var":0},"aead_aegis256.wasm":{"avg":8046460000,"var":0},"aead_chacha20poly1305.wasm":{"avg":179320000,"var":0},"aead_chacha20poly13052.wasm":{"avg":274445000,"var":0},"aead_xchacha20poly1305.wasm":{"avg":158430000,"var":0},"auth.wasm":{"avg":33190000,"var":0},"auth2.wasm":{"avg":1840000,"var":0},"auth3.wasm":{"avg":3380000,"var":0},"auth5.wasm":{"avg":17878600000,"var":0},"auth6.wasm":{"avg":3305000,"var":0},"auth7.wasm":{"avg":9361510000,"var":0},"box.wasm":{"avg":366720000,"var":0},"box2.wasm":{"avg":355370000,"var":0},"box7.wasm":{"avg":347434525000,"var":0},"box8.wasm":{"avg":1044530285000,"var":0},"box_easy.wasm":{"avg":705265000,"var":0},"box_easy2.wasm":{"avg":47015305000,"var":0},"box_seal.wasm":{"avg":1941470000,"var":0},"box_seed.wasm":{"avg":59675000,"var":0},"chacha20.wasm":{"avg":709700000,"var":0},"codecs.wasm":{"avg":1213935000,"var":0},"core3.wasm":{"avg":63306420000,"var":0},"core_ed25519.wasm":{"avg":1272909460000,"var":0},"core_ed25519_h2c.wasm":{"avg":1994980000,"var":0},"core_ristretto255.wasm":{"avg":1393697565000,"var":0},"ed25519_convert.wasm":{"avg":148605125000,"var":0},"generichash.wasm":{"avg":503065000,"var":0},"generichash2.wasm":{"avg":44300000,"var":0},"generichash3.wasm":{"avg":41970000,"var":0},"hash.wasm":{"avg":4435000,"var":0},"hash3.wasm":{"avg":795000,"var":0},"kdf.wasm":{"avg":28385000,"var":0},"kdf_hkdf.wasm":{"avg":836770000,"var":0},"keygen.wasm":{"avg":12445000,"var":0},"kx.wasm":{"avg":2055050000,"var":0},"metamorphic.wasm":{"avg":21795620000,"var":0},"onetimeauth.wasm":{"avg":1020000,"var":0},"onetimeauth2.wasm":{"avg":0,"var":0},"onetimeauth7.wasm":{"avg":5404260000,"var":0},"pwhash_argon2i.wasm":{"avg":341733090000,"var":0},"pwhash_argon2id.wasm":{"avg":390922845000,"var":0},"pwhash_scrypt.wasm":{"avg":1095929635000,"var":0},"pwhash_scrypt_ll.wasm":{"avg":72891585000,"var":0},"randombytes.wasm":{"avg":5554625000,"var":0},"scalarmult.wasm":{"avg":648095000,"var":0},"scalarmult2.wasm":{"avg":58205000,"var":0},"scalarmult5.wasm":{"avg":178005000,"var":0},"scalarmult6.wasm":{"avg":199095000,"var":0},"scalarmult7.wasm":{"avg":366905000,"var":0},"scalarmult8.wasm":{"avg":10456250000,"var":0},"scalarmult_ed25519.wasm":{"avg":3508120000,"var":0},"scalarmult_ristretto255.wasm":{"avg":4208925000,"var":0},"secretbox.wasm":{"avg":2325000,"var":0},"secretbox2.wasm":{"avg":1765000,"var":0},"secretbox7.wasm":{"avg":7861410000,"var":0},"secretbox8.wasm":{"avg":17381120000,"var":0},"secretbox_easy.wasm":{"avg":10500000,"var":0},"secretbox_easy2.wasm":{"avg":29584790000,"var":0},"secretstream_xchacha20poly1305.wasm":{"avg":96875000,"var":0},"shorthash.wasm":{"avg":1825000,"var":0},"sign.wasm":{"avg":618298120000,"var":0},"sign2.wasm":{"avg":987210000,"var":0},"siphashx24.wasm":{"avg":1805000,"var":0},"sodium_utils.wasm":{"avg":18951935000,"var":0},"stream.wasm":{"avg":47990875000,"var":0},"stream2.wasm":{"avg":38985325000,"var":0},"stream3.wasm":{"avg":445000,"var":0},"stream4.wasm":{"avg":905000,"var":0},"verify1.wasm":{"avg":38814510000,"var":0},"xchacha20.wasm":{"avg":11964580000,"var":0}}}}
