{"libsodium-tests":{"repeat":"1","result":{"aead_aegis128l.wasm":{"avg":8264370000,"var":0},"aead_aegis256.wasm":{"avg":9987790000,"var":0},"aead_chacha20poly1305.wasm":{"avg":154510000,"var":0},"aead_chacha20poly13052.wasm":{"avg":269395000,"var":0},"aead_xchacha20poly1305.wasm":{"avg":150330000,"var":0},"auth.wasm":{"avg":34200000,"var":0},"auth2.wasm":{"avg":2135000,"var":0},"auth3.wasm":{"avg":4540000,"var":0},"auth5.wasm":{"avg":18410600000,"var":0},"auth6.wasm":{"avg":3325000,"var":0},"auth7.wasm":{"avg":9863010000,"var":0},"box.wasm":{"avg":353130000,"var":0},"box2.wasm":{"avg":351245000,"var":0},"box7.wasm":{"avg":341629835000,"var":0},"box8.wasm":{"avg":1025153885000,"var":0},"box_easy.wasm":{"avg":693000000,"var":0},"box_easy2.wasm":{"avg":45973035000,"var":0},"box_seal.wasm":{"avg":1884840000,"var":0},"box_seed.wasm":{"avg":59795000,"var":0},"chacha20.wasm":{"avg":660935000,"var":0},"codecs.wasm":{"avg":1348020000,"var":0},"core3.wasm":{"avg":65280770000,"var":0},"core_ed25519.wasm":{"avg":1273497945000,"var":0},"core_ed25519_h2c.wasm":{"avg":1886465000,"var":0},"core_ristretto255.wasm":{"avg":1404652020000,"var":0},"ed25519_convert.wasm":{"avg":149240375000,"var":0},"generichash.wasm":{"avg":472290000,"var":0},"generichash2.wasm":{"avg":45475000,"var":0},"generichash3.wasm":{"avg":42555000,"var":0},"hash.wasm":{"avg":4690000,"var":0},"hash3.wasm":{"avg":805000,"var":0},"kdf.wasm":{"avg":27095000,"var":0},"kdf_hkdf.wasm":{"avg":867435000,"var":0},"keygen.wasm":{"avg":11375000,"var":0},"kx.wasm":{"avg":2030360000,"var":0},"metamorphic.wasm":{"avg":22193675000,"var":0},"onetimeauth.wasm":{"avg":820000,"var":0},"onetimeauth2.wasm":{"avg":0,"var":0},"onetimeauth7.wasm":{"avg":5647615000,"var":0},"pwhash_argon2i.wasm":{"avg":361966645000,"var":0},"pwhash_argon2id.wasm":{"avg":409607700000,"var":0},"pwhash_scrypt.wasm":{"avg":1097240305000,"var":0},"pwhash_scrypt_ll.wasm":{"avg":73796305000,"var":0},"randombytes.wasm":{"avg":5174215000,"var":0},"scalarmult.wasm":{"avg":628525000,"var":0},"scalarmult2.wasm":{"avg":57600000,"var":0},"scalarmult5.wasm":{"avg":172990000,"var":0},"scalarmult6.wasm":{"avg":171235000,"var":0},"scalarmult7.wasm":{"avg":343115000,"var":0},"scalarmult8.wasm":{"avg":10161075000,"var":0},"scalarmult_ed25519.wasm":{"avg":3556425000,"var":0},"scalarmult_ristretto255.wasm":{"avg":4161560000,"var":0},"secretbox.wasm":{"avg":2555000,"var":0},"secretbox2.wasm":{"avg":1735000,"var":0},"secretbox7.wasm":{"avg":7790300000,"var":0},"secretbox8.wasm":{"avg":17691880000,"var":0},"secretbox_easy.wasm":{"avg":11185000,"var":0},"secretbox_easy2.wasm":{"avg":30885290000,"var":0},"secretstream_xchacha20poly1305.wasm":{"avg":96820000,"var":0},"shorthash.wasm":{"avg":1410000,"var":0},"sign.wasm":{"avg":622120340000,"var":0},"sign2.wasm":{"avg":978900000,"var":0},"siphashx24.wasm":{"avg":2380000,"var":0},"sodium_utils.wasm":{"avg":23752995000,"var":0},"stream.wasm":{"avg":49035225000,"var":0},"stream2.wasm":{"avg":40158470000,"var":0},"stream3.wasm":{"avg":430000,"var":0},"stream4.wasm":{"avg":875000,"var":0},"verify1.wasm":{"avg":71166670000,"var":0},"xchacha20.wasm":{"avg":11075315000,"var":0}}}}
