{"libsodium-tests":{"repeat":"1","result":{"aead_aegis128l.wasm":{"avg":11230735000,"var":0},"aead_aegis256.wasm":{"avg":12463435000,"var":0},"aead_chacha20poly1305.wasm":{"avg":282075000,"var":0},"aead_chacha20poly13052.wasm":{"avg":311180000,"var":0},"aead_xchacha20poly1305.wasm":{"avg":199140000,"var":0},"auth.wasm":{"avg":67155000,"var":0},"auth2.wasm":{"avg":3055000,"var":0},"auth3.wasm":{"avg":7780000,"var":0},"auth5.wasm":{"avg":30092320000,"var":0},"auth6.wasm":{"avg":5720000,"var":0},"auth7.wasm":{"avg":16743865000,"var":0},"box.wasm":{"avg":370700000,"var":0},"box2.wasm":{"avg":376650000,"var":0},"box7.wasm":{"avg":366015310000,"var":0},"box8.wasm":{"avg":1113683425000,"var":0},"box_easy.wasm":{"avg":752835000,"var":0},"box_easy2.wasm":{"avg":50051060000,"var":0},"box_seal.wasm":{"avg":2035620000,"var":0},"box_seed.wasm":{"avg":64070000,"var":0},"chacha20.wasm":{"avg":764715000,"var":0},"codecs.wasm":{"avg":1431565000,"var":0},"core3.wasm":{"avg":77445860000,"var":0},"core_ed25519.wasm":{"avg":1336358305000,"var":0},"core_ed25519_h2c.wasm":{"avg":2053540000,"var":0},"core_ristretto255.wasm":{"avg":1497822660000,"var":0},"ed25519_convert.wasm":{"avg":158702870000,"var":0},"generichash.wasm":{"avg":581825000,"var":0},"generichash2.wasm":{"avg":64960000,"var":0},"generichash3.wasm":{"avg":66400000,"var":0},"hash.wasm":{"avg":6310000,"var":0},"hash3.wasm":{"avg":1295000,"var":0},"kdf.wasm":{"avg":50025000,"var":0},"kdf_hkdf.wasm":{"avg":1543515000,"var":0},"keygen.wasm":{"avg":14460000,"var":0},"kx.wasm":{"avg":2195020000,"var":0},"metamorphic.wasm":{"avg":32418760000,"var":0},"onetimeauth.wasm":{"avg":915000,"var":0},"onetimeauth2.wasm":{"avg":0,"var":0},"onetimeauth7.wasm":{"avg":6106570000,"var":0},"pwhash_argon2i.wasm":{"avg":365584495000,"var":0},"pwhash_argon2id.wasm":{"avg":416288310000,"var":0},"pwhash_scrypt.wasm":{"avg":1253369590000,"var":0},"pwhash_scrypt_ll.wasm":{"avg":82581030000,"var":0},"randombytes.wasm":{"avg":5950540000,"var":0},"scalarmult.wasm":{"avg":668150000,"var":0},"scalarmult2.wasm":{"avg":62705000,"var":0},"scalarmult5.wasm":{"avg":181230000,"var":0},"scalarmult6.wasm":{"avg":194955000,"var":0},"scalarmult7.wasm":{"avg":364725000,"var":0},"scalarmult8.wasm":{"avg":10745465000,"var":0},"scalarmult_ed25519.wasm":{"avg":3696855000,"var":0},"scalarmult_ristretto255.wasm":{"avg":4391825000,"var":0},"secretbox.wasm":{"avg":2280000,"var":0},"secretbox2.wasm":{"avg":1705000,"var":0},"secretbox7.wasm":{"avg":8619790000,"var":0},"secretbox8.wasm":{"avg":19777145000,"var":0},"secretbox_easy.wasm":{"avg":14330000,"var":0},"secretbox_easy2.wasm":{"avg":33100330000,"var":0},"secretstream_xchacha20poly1305.wasm":{"avg":107780000,"var":0},"shorthash.wasm":{"avg":1415000,"var":0},"sign.wasm":{"avg":667969145000,"var":0},"sign2.wasm":{"avg":1015145000,"var":0},"siphashx24.wasm":{"avg":2405000,"var":0},"sodium_utils.wasm":{"avg":23691700000,"var":0},"stream.wasm":{"avg":52104255000,"var":0},"stream2.wasm":{"avg":43539360000,"var":0},"stream3.wasm":{"avg":435000,"var":0},"stream4.wasm":{"avg":915000,"var":0},"verify1.wasm":{"avg":77075505000,"var":0},"xchacha20.wasm":{"avg":11776400000,"var":0}}}}
