{"libsodium-tests":{"repeat":"1","result":{"aead_aegis128l.wasm":{"avg":7990550000,"var":0},"aead_aegis256.wasm":{"avg":8592120000,"var":0},"aead_chacha20poly1305.wasm":{"avg":162445000,"var":0},"aead_chacha20poly13052.wasm":{"avg":264125000,"var":0},"aead_xchacha20poly1305.wasm":{"avg":156575000,"var":0},"auth.wasm":{"avg":34940000,"var":0},"auth2.wasm":{"avg":1780000,"var":0},"auth3.wasm":{"avg":3580000,"var":0},"auth5.wasm":{"avg":18152605000,"var":0},"auth6.wasm":{"avg":3445000,"var":0},"auth7.wasm":{"avg":9748580000,"var":0},"box.wasm":{"avg":365205000,"var":0},"box2.wasm":{"avg":367770000,"var":0},"box7.wasm":{"avg":377083125000,"var":0},"box8.wasm":{"avg":1114618150000,"var":0},"box_easy.wasm":{"avg":722660000,"var":0},"box_easy2.wasm":{"avg":40403295000,"var":0},"box_seal.wasm":{"avg":1940810000,"var":0},"box_seed.wasm":{"avg":59850000,"var":0},"chacha20.wasm":{"avg":666525000,"var":0},"codecs.wasm":{"avg":1337950000,"var":0},"core3.wasm":{"avg":63940625000,"var":0},"core_ed25519.wasm":{"avg":1277604700000,"var":0},"core_ed25519_h2c.wasm":{"avg":1919370000,"var":0},"core_ristretto255.wasm":{"avg":1412292570000,"var":0},"ed25519_convert.wasm":{"avg":148898305000,"var":0},"generichash.wasm":{"avg":492335000,"var":0},"generichash2.wasm":{"avg":44035000,"var":0},"generichash3.wasm":{"avg":42775000,"var":0},"hash.wasm":{"avg":4570000,"var":0},"hash3.wasm":{"avg":805000,"var":0},"kdf.wasm":{"avg":28030000,"var":0},"kdf_hkdf.wasm":{"avg":835715000,"var":0},"keygen.wasm":{"avg":12805000,"var":0},"kx.wasm":{"avg":2149175000,"var":0},"metamorphic.wasm":{"avg":21905850000,"var":0},"onetimeauth.wasm":{"avg":830000,"var":0},"onetimeauth2.wasm":{"avg":5000,"var":0},"onetimeauth7.wasm":{"avg":5846610000,"var":0},"pwhash_argon2i.wasm":{"avg":346694745000,"var":0},"pwhash_argon2id.wasm":{"avg":395933555000,"var":0},"pwhash_scrypt.wasm":{"avg":1105845680000,"var":0},"pwhash_scrypt_ll.wasm":{"avg":71525500000,"var":0},"randombytes.wasm":{"avg":5526770000,"var":0},"scalarmult.wasm":{"avg":664730000,"var":0},"scalarmult2.wasm":{"avg":59325000,"var":0},"scalarmult5.wasm":{"avg":176615000,"var":0},"scalarmult6.wasm":{"avg":177685000,"var":0},"scalarmult7.wasm":{"avg":370060000,"var":0},"scalarmult8.wasm":{"avg":10979940000,"var":0},"scalarmult_ed25519.wasm":{"avg":3630355000,"var":0},"scalarmult_ristretto255.wasm":{"avg":4202815000,"var":0},"secretbox.wasm":{"avg":2555000,"var":0},"secretbox2.wasm":{"avg":1475000,"var":0},"secretbox7.wasm":{"avg":7841815000,"var":0},"secretbox8.wasm":{"avg":17451565000,"var":0},"secretbox_easy.wasm":{"avg":10770000,"var":0},"secretbox_easy2.wasm":{"avg":29796490000,"var":0},"secretstream_xchacha20poly1305.wasm":{"avg":92145000,"var":0},"shorthash.wasm":{"avg":1835000,"var":0},"sign.wasm":{"avg":626903035000,"var":0},"sign2.wasm":{"avg":984965000,"var":0},"siphashx24.wasm":{"avg":2295000,"var":0},"sodium_utils.wasm":{"avg":23401980000,"var":0},"stream.wasm":{"avg":47932780000,"var":0},"stream2.wasm":{"avg":39292120000,"var":0},"stream3.wasm":{"avg":440000,"var":0},"stream4.wasm":{"avg":875000,"var":0},"verify1.wasm":{"avg":71944050000,"var":0},"xchacha20.wasm":{"avg":11791745000,"var":0}}}}
